majormode/__init__.py
majormode/tendkid/__init__.py
majormode/tendkid/constant/__init__.py
majormode/tendkid/constant/bus_route.py
majormode/tendkid/constant/cico.py
majormode/tendkid/constant/guardian.py
majormode/tendkid/constant/idr_device.py
majormode/tendkid/constant/notification.py
majormode/tendkid/constant/sort_order.py
majormode/tendkid/constant/team.py
majormode/tendkid/model/__init__.py
majormode/tendkid/model/cico.py
tendkid_core_library-1.0.0.dist-info/LICENSE.md
tendkid_core_library-1.0.0.dist-info/WHEEL
tendkid_core_library-1.0.0.dist-info/METADATA
tendkid_core_library-1.0.0.dist-info/RECORD
